wagtail_external_menu_items/__init__.py
wagtail_external_menu_items/apps.py
wagtail_external_menu_items/exceptions.py
wagtail_external_menu_items/settings.py
wagtail_external_menu_items/wagtail_hooks.py
wagtail_external_menu_items/migrations/__init__.py
wagtail_external_menu_items-0.1.2.dist-info/LICENCE
wagtail_external_menu_items-0.1.2.dist-info/METADATA
wagtail_external_menu_items-0.1.2.dist-info/WHEEL
wagtail_external_menu_items-0.1.2.dist-info/top_level.txt
wagtail_external_menu_items-0.1.2.dist-info/RECORD
