Metadata-Version: 2.1
Name: wagtail-external-menu-items
Version: 0.1.2
Summary: Add external links to Wagtail Dashboard Menu
Home-page: https://github.com/spamz23/wagtail-external-menu-items
Author: Diogo Silva
Author-email: diogosilv30@gmail.com
License: MIT
Platform: UNKNOWN
Classifier: Programming Language :: Python :: 3
Classifier: License :: OSI Approved :: MIT License
Classifier: Operating System :: OS Independent
Requires-Python: >=3.0
Requires-Dist: wagtail (>2.0)
